pytplot/__init__.py
pytplot/count_traces.py
pytplot/data_att_getters_setters.py
pytplot/data_exists.py
pytplot/databar.py
pytplot/del_data.py
pytplot/format_sandbox.py
pytplot/get_data.py
pytplot/get_timespan.py
pytplot/get_ylimits.py
pytplot/is_pseudovariable.py
pytplot/link.py
pytplot/options.py
pytplot/replace_data.py
pytplot/replace_metadata.py
pytplot/spedas_colorbar.py
pytplot/store_data.py
pytplot/time_double.py
pytplot/time_string.py
pytplot/timebar.py
pytplot/timespan.py
pytplot/timestamp.py
pytplot/tlimit.py
pytplot/tnames.py
pytplot/tplot.py
pytplot/tplot_copy.py
pytplot/tplot_names.py
pytplot/tplot_options.py
pytplot/tplot_rename.py
pytplot/tplot_utilities.py
pytplot/tres.py
pytplot/version.txt
pytplot/wildcard_routines.py
pytplot/xlim.py
pytplot/ylim.py
pytplot/zlim.py
pytplot/AncillaryPlots/__init__.py
pytplot/AncillaryPlots/position_mars_2d.py
pytplot/AncillaryPlots/position_mars_3d.py
pytplot/AncillaryPlots/spec_slicer.py
pytplot/MPLPlotter/__init__.py
pytplot/MPLPlotter/annotate.py
pytplot/MPLPlotter/ctime.py
pytplot/MPLPlotter/highlight.py
pytplot/MPLPlotter/lineplot.py
pytplot/MPLPlotter/specplot.py
pytplot/MPLPlotter/tplot.py
pytplot/MPLPlotter/var_labels.py
pytplot/QtPlotter/PyTPlot_Exporter.py
pytplot/QtPlotter/TVarFigure1D.py
pytplot/QtPlotter/TVarFigureAlt.py
pytplot/QtPlotter/TVarFigureAxisOnly.py
pytplot/QtPlotter/TVarFigureMap.py
pytplot/QtPlotter/TVarFigureSpec.py
pytplot/QtPlotter/__init__.py
pytplot/QtPlotter/generate.py
pytplot/QtPlotter/CustomAxis/AxisItem.py
pytplot/QtPlotter/CustomAxis/BlankAxis.py
pytplot/QtPlotter/CustomAxis/DateAxis.py
pytplot/QtPlotter/CustomAxis/NonLinearAxis.py
pytplot/QtPlotter/CustomAxis/__init__.py
pytplot/QtPlotter/CustomImage/ColorbarImage.py
pytplot/QtPlotter/CustomImage/UpdatingImage.py
pytplot/QtPlotter/CustomImage/__init__.py
pytplot/QtPlotter/CustomLegend/CustomLegend.py
pytplot/QtPlotter/CustomLegend/__init__.py
pytplot/QtPlotter/CustomLinearRegionItem/CustomLinearRegionItem.py
pytplot_mpl_temp-2.2.79.dist-info/LICENSE
pytplot_mpl_temp-2.2.79.dist-info/METADATA
pytplot_mpl_temp-2.2.79.dist-info/WHEEL
pytplot_mpl_temp-2.2.79.dist-info/top_level.txt
pytplot_mpl_temp-2.2.79.dist-info/RECORD
