Metadata-Version: 2.1
Name: pytplot-mpl-temp
Version: 2.2.79
Summary: A python version of IDL tplot libraries
Home-page: https://github.com/MAVENSDC/pytplot
Author: MAVEN SDC
Author-email: mavensdc@lasp.colorado.edu
Keywords: tplot,maven,lasp,IDL,spedas
Classifier: Development Status :: 5 - Production/Stable
Classifier: Environment :: Console
Classifier: Intended Audience :: Science/Research
Classifier: Operating System :: OS Independent
Classifier: Programming Language :: Python :: 3
Classifier: Topic :: Utilities
Requires-Python: >=3.9
License-File: LICENSE
Requires-Dist: numpy (>=1.19.5)
Requires-Dist: pandas
Requires-Dist: matplotlib (>=3.6.2)
Requires-Dist: scipy
Requires-Dist: cdflib
Requires-Dist: xarray
Requires-Dist: astropy
Requires-Dist: python-dateutil
Requires-Dist: netCDF4
Provides-Extra: tests
Requires-Dist: pytest ; extra == 'tests'
Requires-Dist: pytest-cov ; extra == 'tests'
Requires-Dist: coveralls ; extra == 'tests'
Requires-Dist: flake8 ; extra == 'tests'
Requires-Dist: mypy ; extra == 'tests'
Requires-Dist: astropy ; extra == 'tests'
